{
  "$schema": "https://cloud.uipath.com/draft/2024-12/entry-point",
  "entryPoints": [
    {
      "filePath": "Main.xaml",
      "uniqueId": "926729f0-eaa9-4782-a586-9097f21c77df",
      "type": "process",
      "input": {
        "type": "object",
        "properties": {
          "in_OrchestratorQueueName": {
            "type": "string",
            "description": "Allows the Orchestrator queue name to be passed as an argument, instead of only being defined in the configuration file."
          },
          "in_OrchestratorQueueFolder": {
            "type": "string",
            "description": "Allows the Orchestrator folder name where the queue is created to be passed as an argument, instead of only being defined in the configuration file."
          }
        },
        "required": []
      }
    }
  ]
}